{"cachedAt":"2026-05-08T14:08:03.407Z","payload":{"ftsAnnual":{"annualRev":[{"value":213237000},{"value":225333000},{"value":234934000},{"value":294839000}],"annualOpInc":[{"value":-10638000},{"value":-10672000},{"value":-27082000},{"value":678000}],"annualGP":[{"value":25067000},{"value":27939000},{"value":10896000},{"value":36093000}],"annualNetIncome":[{"value":-19103000},{"value":-13819000},{"value":-31520000},{"value":-3211000}],"annualFCF":[{"value":-20597000},{"value":-11935000},{"value":5696000},{"value":-23136000}]},"ftsQuarterly":{"revenueQ":[{"value":47965000},{"value":53202000},{"value":50691000},{"value":48773000},{"value":52253000}],"opIncQ":[{"value":-3141000},{"value":-2956000},{"value":-1891000},{"value":-817000},{"value":-2232000}],"grossProfitQ":[{"value":5323000},{"value":5782000},{"value":7228000},{"value":7653000},{"value":6347000}]},"ftsBalance":[{"totalCash":5629000,"totalDebt":12714000,"totalAssets":123370000},{"totalCash":10012000,"totalDebt":null,"totalAssets":132054000},{"totalCash":20964000,"totalDebt":null,"totalAssets":152183000},{"totalCash":14550000,"totalDebt":null,"totalAssets":177563000}],"ftsAnnualSBC":[650000,915000,1145000,1133000],"ftsAnnualCapex":[-2947000,-3711000,-2108000,-5695000],"ftsQuarterlyNI":[-3432000,-4306000,-231000,-2072000,-4126000]}}