{"cachedAt":"2026-05-08T15:04:16.071Z","payload":{"ftsAnnual":{"annualRev":[{"value":313271000},{"value":432681000},{"value":426091000},{"value":546937000}],"annualOpInc":[],"annualGP":[],"annualNetIncome":[{"value":165022000},{"value":238759000},{"value":182655000},{"value":383011000}],"annualFCF":[{"value":153072000},{"value":46926000},{"value":186469000},{"value":434365000}]},"ftsQuarterly":{"revenueQ":[],"opIncQ":[],"grossProfitQ":[]},"ftsBalance":[{"totalCash":168529000,"totalDebt":5110000,"totalAssets":1093756000},{"totalCash":322567000,"totalDebt":7606000,"totalAssets":1089244000},{"totalCash":373445000,"totalDebt":10172000,"totalAssets":1198974000},{"totalCash":419922000,"totalDebt":12552000,"totalAssets":1241401000}],"ftsAnnualSBC":[],"ftsAnnualCapex":[-324000,-458000,-112000,-261000],"ftsQuarterlyNI":[]}}