{
  "identifier": {
    "primary": "ISIN",
    "value": "TICKER:2038.HK"
  },
  "meta": {
    "ticker": "2038.HK",
    "name": "FIH Mobile Limited",
    "sector": "Technology",
    "industry": "Consumer Electronics",
    "region": "HKSE",
    "reportingCurrency": "HKD",
    "fetchedAt": "2026-05-11T16:02:58.672Z",
    "filingDate": null,
    "firstTradeDate": "2005-02-03T01:30:00.000Z",
    "ipoYear": 2005
  },
  "marketCap": {
    "value": 2882373156.864,
    "source": "yahoo_quoteSummary",
    "confidence": 0.9,
    "asOf": "2026-05-11T16:02:58.672Z"
  },
  "metrics": {
    "revenueTTM": {
      "value": 6657662976,
      "source": "yahoo_quoteSummary",
      "confidence": 0.9,
      "asOf": "2026-05-11T16:02:58.672Z"
    },
    "revenueGrowthYoY": {
      "value": 20.7,
      "source": "yahoo_quoteSummary",
      "confidence": 0.9,
      "asOf": "2026-05-11T16:02:58.672Z"
    },
    "grossMargin": {
      "value": 3.083,
      "source": "yahoo_quoteSummary",
      "confidence": 0.9,
      "asOf": "2026-05-11T16:02:58.672Z"
    },
    "operatingMargin": {
      "value": 1.061,
      "source": "yahoo_quoteSummary",
      "confidence": 0.9,
      "asOf": "2026-05-11T16:02:58.672Z"
    },
    "fcfMarginTTM": {
      "value": -2.5820620932554696,
      "source": "yahoo_quoteSummary",
      "confidence": 0.9,
      "asOf": "2026-05-11T16:02:58.672Z"
    },
    "sbcRatio": null,
    "insidersOwnership": {
      "value": 0.66413003,
      "source": "yahoo_quoteSummary",
      "confidence": 0.7,
      "asOf": "2026-05-11T16:02:58.672Z"
    },
    "cashRunway": null,
    "priceSales": {
      "value": 3.382349,
      "source": "yahoo_quoteSummary",
      "confidence": 0.9,
      "asOf": "2026-05-11T16:02:58.672Z"
    },
    "forwardPE": {
      "value": 360.75003,
      "source": "yahoo_quoteSummary",
      "confidence": 0.9,
      "asOf": "2026-05-11T16:02:58.672Z"
    },
    "pe": {
      "value": 54.452835,
      "source": "yahoo_quoteSummary",
      "confidence": 0.9,
      "asOf": "2026-05-11T16:02:58.672Z"
    }
  },
  "external": {},
  "timeseries": {
    "revenueQ": [
      {
        "value": 3070869000
      },
      {
        "value": 2008060000
      }
    ],
    "opIncQ": [],
    "grossProfitQ": [
      {
        "value": 0
      },
      {
        "value": 0
      }
    ],
    "netIncomeQ": []
  },
  "annual": {
    "annualRev": [
      {
        "value": 0
      },
      {
        "value": 0
      },
      {
        "value": 9394319000
      },
      {
        "value": 8582559000
      }
    ],
    "annualOpInc": [
      {
        "value": -73413000
      },
      {
        "value": -31770000
      }
    ],
    "annualNetIncome": [
      {
        "value": -20331000
      },
      {
        "value": -120680000
      },
      {
        "value": -72107000
      },
      {
        "value": 56328000
      }
    ],
    "annualGP": [
      {
        "value": 205229000
      },
      {
        "value": 134640000
      },
      {
        "value": 109816000
      },
      {
        "value": 191956000
      }
    ],
    "annualFCF": [
      {
        "value": -78835000
      },
      {
        "value": 237227000
      },
      {
        "value": 9483000
      },
      {
        "value": 266119000
      }
    ],
    "annualBalance": [
      {
        "totalCash": 1006882000,
        "totalDebt": 108370000,
        "totalAssets": 3744004000
      },
      {
        "totalCash": 1516241000,
        "totalDebt": 341420000,
        "totalAssets": 3822023000
      },
      {
        "totalCash": 1845323000,
        "totalDebt": 703676000,
        "totalAssets": 4319436000
      },
      {
        "totalCash": 1825109000,
        "totalDebt": 676054000,
        "totalAssets": 5510290000
      }
    ],
    "annualSBC": [
      14183000,
      526000,
      1291000,
      10200000
    ],
    "annualCapex": [
      -186653000,
      -125009000,
      -93174000,
      -143295000
    ]
  }
}