{
  "identifier": {
    "primary": "ISIN",
    "value": "TICKER:3311.HK"
  },
  "meta": {
    "ticker": "3311.HK",
    "name": "China State Construction International Holdings Limited",
    "sector": "Industrials",
    "industry": "Engineering & Construction",
    "region": "HKSE",
    "reportingCurrency": "HKD",
    "fetchedAt": "2026-05-09T08:48:04.791Z",
    "filingDate": null,
    "firstTradeDate": "2000-01-04T01:30:00.000Z",
    "ipoYear": 2000
  },
  "marketCap": {
    "value": 6342040354.816,
    "source": "yahoo_quoteSummary",
    "confidence": 0.9,
    "asOf": "2026-05-09T08:48:04.791Z"
  },
  "metrics": {
    "revenueTTM": {
      "value": 100448501760,
      "source": "yahoo_quoteSummary",
      "confidence": 0.9,
      "asOf": "2026-05-09T08:48:04.791Z"
    },
    "revenueGrowthYoY": {
      "value": -10.2,
      "source": "yahoo_quoteSummary",
      "confidence": 0.9,
      "asOf": "2026-05-09T08:48:04.791Z"
    },
    "grossMargin": {
      "value": 15.909999999999998,
      "source": "yahoo_quoteSummary",
      "confidence": 0.9,
      "asOf": "2026-05-09T08:48:04.791Z"
    },
    "operatingMargin": {
      "value": 13.444,
      "source": "yahoo_quoteSummary",
      "confidence": 0.9,
      "asOf": "2026-05-09T08:48:04.791Z"
    },
    "fcfMarginTTM": {
      "value": -0.5439496243612265,
      "source": "yahoo_quoteSummary",
      "confidence": 0.9,
      "asOf": "2026-05-09T08:48:04.791Z"
    },
    "sbcRatio": null,
    "insidersOwnership": {
      "value": 0.69851,
      "source": "yahoo_quoteSummary",
      "confidence": 0.7,
      "asOf": "2026-05-09T08:48:04.791Z"
    },
    "cashRunway": null,
    "priceSales": {
      "value": 0.49325964,
      "source": "yahoo_quoteSummary",
      "confidence": 0.9,
      "asOf": "2026-05-09T08:48:04.791Z"
    },
    "forwardPE": {
      "value": 4.562723,
      "source": "yahoo_quoteSummary",
      "confidence": 0.9,
      "asOf": "2026-05-09T08:48:04.791Z"
    },
    "pe": {
      "value": 4.962963,
      "source": "yahoo_quoteSummary",
      "confidence": 0.9,
      "asOf": "2026-05-09T08:48:04.791Z"
    }
  },
  "external": {},
  "timeseries": {
    "revenueQ": [
      {
        "value": 13593190000
      },
      {
        "value": 7382647000
      },
      {
        "value": 3071505000
      }
    ],
    "opIncQ": [],
    "grossProfitQ": [
      {
        "value": 0
      },
      {
        "value": 0
      },
      {
        "value": 0
      }
    ],
    "netIncomeQ": []
  },
  "annual": {
    "annualRev": [
      {
        "value": 113783801380
      },
      {
        "value": 115106744000
      },
      {
        "value": 113734013000
      },
      {
        "value": 101975265000
      }
    ],
    "annualOpInc": [
      {
        "value": 13329956000
      },
      {
        "value": 13747546000
      },
      {
        "value": 12442227889.561445
      },
      {
        "value": 10228437635.08031
      }
    ],
    "annualNetIncome": [
      {
        "value": 9728624050
      },
      {
        "value": 9361017000
      },
      {
        "value": 9164045000
      },
      {
        "value": 7956876000
      }
    ],
    "annualGP": [
      {
        "value": 15981699000
      },
      {
        "value": 16329572000
      },
      {
        "value": 14821544786.609165
      },
      {
        "value": 12378327859.077238
      }
    ],
    "annualFCF": [
      {
        "value": 84210000
      },
      {
        "value": 783181000
      },
      {
        "value": -58443780.274625
      },
      {
        "value": -133106556.498368
      }
    ],
    "annualBalance": [
      {
        "totalCash": 30328604000,
        "totalDebt": 85557356000,
        "totalAssets": 280689299000
      },
      {
        "totalCash": 28589158000,
        "totalDebt": 81129930000,
        "totalAssets": 263437882000
      },
      {
        "totalCash": 25844303000,
        "totalDebt": 73449321000,
        "totalAssets": 234716142000
      },
      {
        "totalCash": 21081678915.671593,
        "totalDebt": 65830689708.222946,
        "totalAssets": 202074063481.11603
      }
    ],
    "annualSBC": [
      6768000,
      5959855.905199,
      30134051.462213
    ],
    "annualCapex": [
      -968963000,
      -1053642000,
      -512911367.697682,
      -320407076.969348
    ]
  }
}