{
  "identifier": {
    "primary": "ISIN",
    "value": "TICKER:601669.SS"
  },
  "meta": {
    "ticker": "601669.SS",
    "name": "Power Construction Corporation of China, Ltd",
    "sector": "Industrials",
    "industry": "Engineering & Construction",
    "region": "Shanghai",
    "reportingCurrency": "CNY",
    "fetchedAt": "2026-05-13T03:54:20.360Z",
    "filingDate": null,
    "firstTradeDate": "2011-10-18T01:30:00.000Z",
    "ipoYear": 2011
  },
  "marketCap": {
    "value": 14582117097.472002,
    "source": "yahoo_quoteSummary",
    "confidence": 0.9,
    "asOf": "2026-05-13T03:54:20.360Z"
  },
  "metrics": {
    "revenueTTM": {
      "value": 648108113920,
      "source": "yahoo_quoteSummary",
      "confidence": 0.9,
      "asOf": "2026-05-13T03:54:20.360Z"
    },
    "revenueGrowthYoY": {
      "value": 1.7000000000000002,
      "source": "yahoo_quoteSummary",
      "confidence": 0.9,
      "asOf": "2026-05-13T03:54:20.360Z"
    },
    "grossMargin": {
      "value": 12.281,
      "source": "yahoo_quoteSummary",
      "confidence": 0.9,
      "asOf": "2026-05-13T03:54:20.360Z"
    },
    "operatingMargin": {
      "value": 4.414,
      "source": "yahoo_quoteSummary",
      "confidence": 0.9,
      "asOf": "2026-05-13T03:54:20.360Z"
    },
    "fcfMarginTTM": {
      "value": -1.161369493505384,
      "source": "yahoo_quoteSummary",
      "confidence": 0.9,
      "asOf": "2026-05-13T03:54:20.360Z"
    },
    "sbcRatio": null,
    "insidersOwnership": {
      "value": 0.53687,
      "source": "yahoo_quoteSummary",
      "confidence": 0.7,
      "asOf": "2026-05-13T03:54:20.360Z"
    },
    "cashRunway": null,
    "priceSales": {
      "value": 0.16186701,
      "source": "yahoo_quoteSummary",
      "confidence": 0.9,
      "asOf": "2026-05-13T03:54:20.360Z"
    },
    "forwardPE": {
      "value": 6.920455,
      "source": "yahoo_quoteSummary",
      "confidence": 0.9,
      "asOf": "2026-05-13T03:54:20.360Z"
    },
    "pe": {
      "value": 12.428572,
      "source": "yahoo_quoteSummary",
      "confidence": 0.9,
      "asOf": "2026-05-13T03:54:20.360Z"
    }
  },
  "external": {},
  "timeseries": {
    "revenueQ": [
      {
        "value": 145237333379.11
      },
      {
        "value": 206684423545.11
      },
      {
        "value": 150319346592.61
      },
      {
        "value": 142760042240.3
      },
      {
        "value": 208205245672.62
      }
    ],
    "opIncQ": [
      {
        "value": 6738024210.97
      },
      {
        "value": 12343169371.47
      },
      {
        "value": 7798052345.9
      },
      {
        "value": 7205934329.43
      },
      {
        "value": 13033295211.46
      }
    ],
    "grossProfitQ": [
      {
        "value": 14926826331.48
      },
      {
        "value": 29999839200.42
      },
      {
        "value": 17584878720.98
      },
      {
        "value": 15575592556.35
      },
      {
        "value": 30890480641.31
      }
    ],
    "netIncomeQ": [
      {
        "value": 1951116531.21
      },
      {
        "value": 2533505130.56
      },
      {
        "value": 2790566246.46
      },
      {
        "value": 2620973436.7
      },
      {
        "value": 3208713464.76
      }
    ]
  },
  "annual": {
    "annualRev": [
      {
        "value": 645604120330
      },
      {
        "value": 633684805910
      },
      {
        "value": 608439218600
      },
      {
        "value": 571649324370
      }
    ],
    "annualOpInc": [
      {
        "value": 34040850250.29
      },
      {
        "value": 37851275190.34
      },
      {
        "value": 37088384761.29
      },
      {
        "value": 30492683289.12
      }
    ],
    "annualNetIncome": [
      {
        "value": 10007143580
      },
      {
        "value": 12015017080
      },
      {
        "value": 12988385290
      },
      {
        "value": 11435443830
      }
    ],
    "annualGP": [
      {
        "value": 80862022317.86
      },
      {
        "value": 84455083036.72
      },
      {
        "value": 81503643605.18
      },
      {
        "value": 70752458874.31
      }
    ],
    "annualFCF": [
      {
        "value": -13649482737.58
      },
      {
        "value": -34542597044.89
      },
      {
        "value": -51494704151.56
      },
      {
        "value": -26918818383.19
      }
    ],
    "annualBalance": [
      {
        "totalCash": 127924734154.84,
        "totalDebt": 464716129611.43,
        "totalAssets": 1380267054189.34
      },
      {
        "totalCash": 115065869475.11,
        "totalDebt": 423409189110.7,
        "totalAssets": 1289068744119.64
      },
      {
        "totalCash": 97651977175.82,
        "totalDebt": 355476190738.94995,
        "totalAssets": 1154554851369.64
      },
      {
        "totalCash": 100954717358.59,
        "totalDebt": 323003023301.23,
        "totalAssets": 1040110429016.84
      }
    ],
    "annualSBC": [],
    "annualCapex": [
      -44346133876.58,
      -59090494944.56,
      -73739449266.6,
      -57750520903.93
    ]
  }
}