{
  "identifier": {
    "primary": "ISIN",
    "value": "TICKER:BCC"
  },
  "meta": {
    "ticker": "BCC",
    "name": "Boise Cascade Company",
    "sector": "Basic Materials",
    "industry": "Lumber & Wood Production",
    "region": "NYSE",
    "reportingCurrency": "USD",
    "fetchedAt": "2026-05-08T19:37:05.722Z",
    "filingDate": null,
    "firstTradeDate": "2013-02-06T14:30:00.000Z",
    "ipoYear": 2013
  },
  "marketCap": {
    "value": 2491081472,
    "source": "yahoo_quoteSummary",
    "confidence": 0.9,
    "asOf": "2026-05-08T19:37:05.722Z"
  },
  "metrics": {
    "revenueTTM": {
      "value": 6366714880,
      "source": "yahoo_quoteSummary",
      "confidence": 0.9,
      "asOf": "2026-05-08T19:37:05.722Z"
    },
    "revenueGrowthYoY": {
      "value": -2.5,
      "source": "yahoo_quoteSummary",
      "confidence": 0.9,
      "asOf": "2026-05-08T19:37:05.722Z"
    },
    "grossMargin": {
      "value": 16.290002,
      "source": "yahoo_quoteSummary",
      "confidence": 0.9,
      "asOf": "2026-05-08T19:37:05.722Z"
    },
    "operatingMargin": {
      "value": 1.8519999999999999,
      "source": "yahoo_quoteSummary",
      "confidence": 0.9,
      "asOf": "2026-05-08T19:37:05.722Z"
    },
    "fcfMarginTTM": {
      "value": -0.39544136143253833,
      "source": "yahoo_quoteSummary",
      "confidence": 0.9,
      "asOf": "2026-05-08T19:37:05.722Z"
    },
    "sbcRatio": null,
    "insidersOwnership": {
      "value": 0.012309999,
      "source": "yahoo_quoteSummary",
      "confidence": 0.7,
      "asOf": "2026-05-08T19:37:05.722Z"
    },
    "cashRunway": null,
    "priceSales": {
      "value": 0.39126638,
      "source": "yahoo_quoteSummary",
      "confidence": 0.9,
      "asOf": "2026-05-08T19:37:05.722Z"
    },
    "forwardPE": {
      "value": 13.056863,
      "source": "yahoo_quoteSummary",
      "confidence": 0.9,
      "asOf": "2026-05-08T19:37:05.722Z"
    },
    "pe": {
      "value": 23.835016,
      "source": "yahoo_quoteSummary",
      "confidence": 0.9,
      "asOf": "2026-05-08T19:37:05.722Z"
    }
  },
  "external": {},
  "timeseries": {
    "revenueQ": [
      {
        "value": 1460181000
      },
      {
        "value": 1667806000
      },
      {
        "value": 1740114000
      },
      {
        "value": 1536494000
      },
      {
        "value": 1567480000
      }
    ],
    "opIncQ": [
      {
        "value": 15918000
      },
      {
        "value": 32296000
      },
      {
        "value": 80498000
      },
      {
        "value": 54486000
      },
      {
        "value": 92681000
      }
    ],
    "grossProfitQ": [
      {
        "value": 231432000
      },
      {
        "value": 263495000
      },
      {
        "value": 298655000
      },
      {
        "value": 260311000
      },
      {
        "value": 297711000
      }
    ],
    "netIncomeQ": [
      {
        "value": 8734000
      },
      {
        "value": 21769000
      },
      {
        "value": 61985000
      },
      {
        "value": 40348000
      },
      {
        "value": 68900000
      }
    ]
  },
  "annual": {
    "annualRev": [
      {
        "value": 6404595000
      },
      {
        "value": 6724294000
      },
      {
        "value": 6838245000
      },
      {
        "value": 8387307000
      }
    ],
    "annualOpInc": [
      {
        "value": 183198000
      },
      {
        "value": 489889000
      },
      {
        "value": 624223000
      },
      {
        "value": 1157555000
      }
    ],
    "annualNetIncome": [
      {
        "value": 132836000
      },
      {
        "value": 376354000
      },
      {
        "value": 483656000
      },
      {
        "value": 857658000
      }
    ],
    "annualGP": [
      {
        "value": 1053893000
      },
      {
        "value": 1330687000
      },
      {
        "value": 1428934000
      },
      {
        "value": 1914767000
      }
    ],
    "annualFCF": [
      {
        "value": 12717000
      },
      {
        "value": 208751000
      },
      {
        "value": 472020000
      },
      {
        "value": 927102000
      }
    ],
    "annualBalance": [
      {
        "totalCash": 477215000,
        "totalDebt": 445405000,
        "totalAssets": 3241943000
      },
      {
        "totalCash": 713260000,
        "totalDebt": 446167000,
        "totalAssets": 3369383000
      },
      {
        "totalCash": 949574000,
        "totalDebt": 445280000,
        "totalAssets": 3458646000
      },
      {
        "totalCash": 998344000,
        "totalDebt": 444392000,
        "totalAssets": 3240514000
      }
    ],
    "annualSBC": [
      12119000,
      15486000,
      15410000,
      11870000
    ],
    "annualCapex": [
      -241431000,
      -229569000,
      -215438000,
      -114117000
    ]
  }
}