{
  "identifier": {
    "primary": "ISIN",
    "value": "TICKER:BCE"
  },
  "meta": {
    "ticker": "BCE",
    "name": "BCE Inc.",
    "sector": "Communication Services",
    "industry": "Telecom Services",
    "region": "NYSE",
    "reportingCurrency": "USD",
    "fetchedAt": "2026-05-09T15:37:03.656Z",
    "filingDate": null,
    "firstTradeDate": "1982-11-15T14:30:00.000Z",
    "ipoYear": 1982
  },
  "marketCap": {
    "value": 22511173632,
    "source": "yahoo_quoteSummary",
    "confidence": 0.9,
    "asOf": "2026-05-09T15:37:03.656Z"
  },
  "metrics": {
    "revenueTTM": {
      "value": 24706000896,
      "source": "yahoo_quoteSummary",
      "confidence": 0.9,
      "asOf": "2026-05-09T15:37:03.656Z"
    },
    "revenueGrowthYoY": {
      "value": 4,
      "source": "yahoo_quoteSummary",
      "confidence": 0.9,
      "asOf": "2026-05-09T15:37:03.656Z"
    },
    "grossMargin": {
      "value": 44.957,
      "source": "yahoo_quoteSummary",
      "confidence": 0.9,
      "asOf": "2026-05-09T15:37:03.656Z"
    },
    "operatingMargin": {
      "value": 21.271,
      "source": "yahoo_quoteSummary",
      "confidence": 0.9,
      "asOf": "2026-05-09T15:37:03.656Z"
    },
    "fcfMarginTTM": {
      "value": 10.853132351477107,
      "source": "yahoo_quoteSummary",
      "confidence": 0.9,
      "asOf": "2026-05-09T15:37:03.656Z"
    },
    "sbcRatio": null,
    "insidersOwnership": {
      "value": 0.00031,
      "source": "yahoo_quoteSummary",
      "confidence": 0.7,
      "asOf": "2026-05-09T15:37:03.656Z"
    },
    "cashRunway": null,
    "priceSales": {
      "value": 0.9111622,
      "source": "yahoo_quoteSummary",
      "confidence": 0.9,
      "asOf": "2026-05-09T15:37:03.656Z"
    },
    "forwardPE": {
      "value": 12.135866,
      "source": "yahoo_quoteSummary",
      "confidence": 0.9,
      "asOf": "2026-05-09T15:37:03.656Z"
    },
    "pe": {
      "value": 4.8669353,
      "source": "yahoo_quoteSummary",
      "confidence": 0.9,
      "asOf": "2026-05-09T15:37:03.656Z"
    }
  },
  "external": {},
  "timeseries": {
    "revenueQ": [
      {
        "value": 6404000000
      },
      {
        "value": 6049000000
      },
      {
        "value": 6085000000
      },
      {
        "value": 5930000000
      },
      {
        "value": 6422000000
      }
    ],
    "opIncQ": [
      {
        "value": 1294000000
      },
      {
        "value": 1453000000
      },
      {
        "value": 1387000000
      },
      {
        "value": 1286000000
      },
      {
        "value": 1355000000
      }
    ],
    "grossProfitQ": [
      {
        "value": 4251000000
      },
      {
        "value": 4284000000
      },
      {
        "value": 4173000000
      },
      {
        "value": 4040000000
      },
      {
        "value": 4135000000
      }
    ],
    "netIncomeQ": [
      {
        "value": 630000000
      },
      {
        "value": 4540000000
      },
      {
        "value": 619000000
      },
      {
        "value": 671000000
      },
      {
        "value": 504000000
      }
    ]
  },
  "annual": {
    "annualRev": [
      {
        "value": 24468000000
      },
      {
        "value": 24409000000
      },
      {
        "value": 24673000000
      },
      {
        "value": 24174000000
      }
    ],
    "annualOpInc": [
      {
        "value": 5420000000
      },
      {
        "value": 5548000000
      },
      {
        "value": 5499000000
      },
      {
        "value": 5476000000
      }
    ],
    "annualNetIncome": [
      {
        "value": 6305000000
      },
      {
        "value": 163000000
      },
      {
        "value": 2076000000
      },
      {
        "value": 2716000000
      }
    ],
    "annualGP": [
      {
        "value": 16748000000
      },
      {
        "value": 16704000000
      },
      {
        "value": 16747000000
      },
      {
        "value": 16533000000
      }
    ],
    "annualFCF": [
      {
        "value": 3290000000
      },
      {
        "value": 2560000000
      },
      {
        "value": 3182000000
      },
      {
        "value": 3229000000
      }
    ],
    "annualBalance": [
      {
        "totalCash": 320000000,
        "totalDebt": 40126000000,
        "totalAssets": 80165000000
      },
      {
        "totalCash": 1572000000,
        "totalDebt": 39416000000,
        "totalAssets": 73485000000
      },
      {
        "totalCash": 772000000,
        "totalDebt": 35103000000,
        "totalAssets": 71940000000
      },
      {
        "totalCash": 149000000,
        "totalDebt": 30990000000,
        "totalAssets": 69329000000
      }
    ],
    "annualSBC": [],
    "annualCapex": [
      -3703000000,
      -4428000000,
      -4764000000,
      -5136000000
    ]
  }
}