{
  "identifier": {
    "primary": "ISIN",
    "value": "TICKER:EVR"
  },
  "meta": {
    "ticker": "EVR",
    "name": "Evercore Inc.",
    "sector": "Financial Services",
    "industry": "Capital Markets",
    "region": "NYSE",
    "reportingCurrency": "USD",
    "fetchedAt": "2026-05-09T08:45:04.015Z",
    "filingDate": null,
    "firstTradeDate": "2006-08-14T13:30:00.000Z",
    "ipoYear": 2006
  },
  "marketCap": {
    "value": 13198076928,
    "source": "yahoo_quoteSummary",
    "confidence": 0.9,
    "asOf": "2026-05-09T08:45:04.015Z"
  },
  "metrics": {
    "revenueTTM": {
      "value": 4553624064,
      "source": "yahoo_quoteSummary",
      "confidence": 0.9,
      "asOf": "2026-05-09T08:45:04.015Z"
    },
    "revenueGrowthYoY": {
      "value": 100.29999999999998,
      "source": "yahoo_quoteSummary",
      "confidence": 0.9,
      "asOf": "2026-05-09T08:45:04.015Z"
    },
    "grossMargin": {
      "value": 94.135004,
      "source": "yahoo_quoteSummary",
      "confidence": 0.9,
      "asOf": "2026-05-09T08:45:04.015Z"
    },
    "operatingMargin": {
      "value": 24.490999,
      "source": "yahoo_quoteSummary",
      "confidence": 0.9,
      "asOf": "2026-05-09T08:45:04.015Z"
    },
    "fcfMarginTTM": null,
    "sbcRatio": null,
    "insidersOwnership": {
      "value": 0.02377,
      "source": "yahoo_quoteSummary",
      "confidence": 0.7,
      "asOf": "2026-05-09T08:45:04.015Z"
    },
    "cashRunway": null,
    "priceSales": {
      "value": 2.8983676,
      "source": "yahoo_quoteSummary",
      "confidence": 0.9,
      "asOf": "2026-05-09T08:45:04.015Z"
    },
    "forwardPE": {
      "value": 14.820629,
      "source": "yahoo_quoteSummary",
      "confidence": 0.9,
      "asOf": "2026-05-09T08:45:04.015Z"
    },
    "pe": {
      "value": 19.189539,
      "source": "yahoo_quoteSummary",
      "confidence": 0.9,
      "asOf": "2026-05-09T08:45:04.015Z"
    }
  },
  "external": {},
  "timeseries": {
    "revenueQ": [
      {
        "value": 1391578000
      },
      {
        "value": 1288277000
      },
      {
        "value": 1038884000
      },
      {
        "value": 833830000
      },
      {
        "value": 694829000
      }
    ],
    "opIncQ": [],
    "grossProfitQ": [
      {
        "value": 0
      },
      {
        "value": 0
      },
      {
        "value": 0
      },
      {
        "value": 0
      }
    ],
    "netIncomeQ": [
      {
        "value": 301235000
      },
      {
        "value": 203954000
      },
      {
        "value": 144583000
      },
      {
        "value": 97201000
      },
      {
        "value": 146184000
      }
    ]
  },
  "annual": {
    "annualRev": [
      {
        "value": 3883956000
      },
      {
        "value": 3002635000
      },
      {
        "value": 2449321000
      },
      {
        "value": 2785603000
      }
    ],
    "annualOpInc": [],
    "annualNetIncome": [
      {
        "value": 591922000
      },
      {
        "value": 378279000
      },
      {
        "value": 255479000
      },
      {
        "value": 476520000
      }
    ],
    "annualGP": [
      {
        "value": 0
      },
      {
        "value": 0
      },
      {
        "value": 0
      },
      {
        "value": 0
      }
    ],
    "annualFCF": [
      {
        "value": 1182462000
      },
      {
        "value": 958050000
      },
      {
        "value": 437906000
      },
      {
        "value": 508189000
      }
    ],
    "annualBalance": [
      {
        "totalCash": 1466441000,
        "totalDebt": 588224000,
        "totalAssets": 5358097000
      },
      {
        "totalCash": 939705000,
        "totalDebt": 373895000,
        "totalAssets": 4173971000
      },
      {
        "totalCash": 651734000,
        "totalDebt": 373885000,
        "totalAssets": 3703298000
      },
      {
        "totalCash": 786290000,
        "totalDebt": 371774000,
        "totalAssets": 3620923000
      }
    ],
    "annualSBC": [
      675100000,
      569734000,
      515381000,
      467339000
    ],
    "annualCapex": [
      -74002000,
      -30101000,
      -20048000,
      -23187000
    ]
  }
}