{
  "identifier": {
    "primary": "ISIN",
    "value": "TICKER:KEY"
  },
  "meta": {
    "ticker": "KEY",
    "name": "KeyCorp",
    "sector": "Financial Services",
    "industry": "Banks - Regional",
    "region": "NYSE",
    "reportingCurrency": "USD",
    "fetchedAt": "2026-05-08T11:13:08.718Z",
    "filingDate": null
  },
  "marketCap": {
    "value": 23516854272,
    "source": "yahoo_quoteSummary",
    "confidence": 0.9,
    "asOf": "2026-05-08T11:13:08.718Z"
  },
  "metrics": {
    "revenueTTM": {
      "value": 7200999936,
      "source": "yahoo_quoteSummary",
      "confidence": 0.9,
      "asOf": "2026-05-08T11:13:08.718Z"
    },
    "revenueGrowthYoY": {
      "value": 11.799999999999999,
      "source": "yahoo_quoteSummary",
      "confidence": 0.9,
      "asOf": "2026-05-08T11:13:08.718Z"
    },
    "grossMargin": {
      "value": 0,
      "source": "yahoo_quoteSummary",
      "confidence": 0.9,
      "asOf": "2026-05-08T11:13:08.718Z"
    },
    "operatingMargin": {
      "value": 35.779998,
      "source": "yahoo_quoteSummary",
      "confidence": 0.9,
      "asOf": "2026-05-08T11:13:08.718Z"
    },
    "fcfMarginTTM": null,
    "sbcRatio": null,
    "insidersOwnership": {
      "value": 0.0028799998,
      "source": "yahoo_quoteSummary",
      "confidence": 0.7,
      "asOf": "2026-05-08T11:13:08.718Z"
    },
    "cashRunway": null,
    "priceSales": {
      "value": 3.2657762,
      "source": "yahoo_quoteSummary",
      "confidence": 0.9,
      "asOf": "2026-05-08T11:13:08.718Z"
    },
    "forwardPE": {
      "value": 10.099034,
      "source": "yahoo_quoteSummary",
      "confidence": 0.9,
      "asOf": "2026-05-08T11:13:08.718Z"
    },
    "pe": {
      "value": 13.306748,
      "source": "yahoo_quoteSummary",
      "confidence": 0.9,
      "asOf": "2026-05-08T11:13:08.718Z"
    }
  },
  "external": {},
  "timeseries": {
    "revenueQ": [
      {
        "value": 1909000000
      },
      {
        "value": 1936000000
      },
      {
        "value": 1842000000
      },
      {
        "value": 1783000000
      },
      {
        "value": 1724000000
      }
    ],
    "opIncQ": [],
    "grossProfitQ": [
      {
        "value": 0
      },
      {
        "value": 0
      },
      {
        "value": 0
      },
      {
        "value": 0
      }
    ],
    "netIncomeQ": [
      {
        "value": 522000000
      },
      {
        "value": 510000000
      },
      {
        "value": 489000000
      },
      {
        "value": 425000000
      },
      {
        "value": 405000000
      }
    ]
  },
  "annual": {
    "annualRev": [
      {
        "value": 7513000000
      },
      {
        "value": 4619000000
      },
      {
        "value": 6413000000
      },
      {
        "value": 7272000000
      }
    ],
    "annualOpInc": [],
    "annualNetIncome": [
      {
        "value": 1686000000
      },
      {
        "value": -304000000
      },
      {
        "value": 824000000
      },
      {
        "value": 1799000000
      }
    ],
    "annualGP": [
      {
        "value": 0
      },
      {
        "value": 0
      },
      {
        "value": 0
      },
      {
        "value": 0
      }
    ],
    "annualFCF": [
      {
        "value": 2101000000
      },
      {
        "value": 599000000
      },
      {
        "value": 2761000000
      },
      {
        "value": 4361000000
      }
    ],
    "annualBalance": [
      {
        "totalCash": 1287000000,
        "totalDebt": 10988000000,
        "totalAssets": 184381000000
      },
      {
        "totalCash": 1743000000,
        "totalDebt": 14235000000,
        "totalAssets": 187168000000
      },
      {
        "totalCash": 941000000,
        "totalDebt": 22602000000,
        "totalAssets": 188281000000
      },
      {
        "totalCash": 887000000,
        "totalDebt": 24688000000,
        "totalAssets": 189813000000
      }
    ],
    "annualSBC": [
      132000000,
      104000000,
      121000000,
      120000000
    ],
    "annualCapex": [
      -107000000,
      -65000000,
      -142000000,
      -108000000
    ]
  }
}