{
  "identifier": {
    "primary": "ISIN",
    "value": "TICKER:LU"
  },
  "meta": {
    "ticker": "LU",
    "name": "Lufax Holding Ltd",
    "sector": "Financial Services",
    "industry": "Credit Services",
    "region": "NYSE",
    "reportingCurrency": "USD",
    "fetchedAt": "2026-05-08T05:28:57.432Z",
    "filingDate": null
  },
  "marketCap": {
    "value": 1690043392,
    "source": "yahoo_quoteSummary",
    "confidence": 0.9,
    "asOf": "2026-05-08T05:28:57.432Z"
  },
  "metrics": {
    "revenueTTM": {
      "value": 27127609344,
      "source": "yahoo_quoteSummary",
      "confidence": 0.9,
      "asOf": "2026-05-08T05:28:57.432Z"
    },
    "revenueGrowthYoY": null,
    "grossMargin": {
      "value": 24.816,
      "source": "yahoo_quoteSummary",
      "confidence": 0.9,
      "asOf": "2026-05-08T05:28:57.432Z"
    },
    "operatingMargin": {
      "value": -6.549,
      "source": "yahoo_quoteSummary",
      "confidence": 0.9,
      "asOf": "2026-05-08T05:28:57.432Z"
    },
    "fcfMarginTTM": {
      "value": 29.42678200195185,
      "source": "yahoo_quoteSummary",
      "confidence": 0.9,
      "asOf": "2026-05-08T05:28:57.432Z"
    },
    "sbcRatio": null,
    "insidersOwnership": {
      "value": 0.01903,
      "source": "yahoo_quoteSummary",
      "confidence": 0.7,
      "asOf": "2026-05-08T05:28:57.432Z"
    },
    "cashRunway": null,
    "priceSales": {
      "value": 0.062299754,
      "source": "yahoo_quoteSummary",
      "confidence": 0.9,
      "asOf": "2026-05-08T05:28:57.432Z"
    },
    "forwardPE": {
      "value": 8.166418,
      "source": "yahoo_quoteSummary",
      "confidence": 0.9,
      "asOf": "2026-05-08T05:28:57.432Z"
    },
    "pe": null
  },
  "external": {},
  "timeseries": {
    "revenueQ": [
      {
        "value": 5976217000
      },
      {
        "value": 6963764000
      },
      {
        "value": 6856820000
      },
      {
        "value": 8050472000
      }
    ],
    "opIncQ": [],
    "grossProfitQ": [
      {
        "value": 0
      },
      {
        "value": 0
      },
      {
        "value": 0
      },
      {
        "value": 0
      }
    ]
  },
  "annual": {
    "annualRev": [
      {
        "value": 27127610000
      },
      {
        "value": 24513408000
      },
      {
        "value": 34255366000
      },
      {
        "value": 58115728000
      }
    ],
    "annualOpInc": [],
    "annualNetIncome": [
      {
        "value": -2097678000
      },
      {
        "value": -3870620000
      },
      {
        "value": 886865000
      },
      {
        "value": 8699369000
      }
    ],
    "annualGP": [
      {
        "value": 0
      },
      {
        "value": 0
      },
      {
        "value": 0
      },
      {
        "value": 0
      }
    ],
    "annualFCF": [
      {
        "value": 12436350000
      },
      {
        "value": 1744206000
      },
      {
        "value": 12669133000
      },
      {
        "value": 4825691000
      }
    ],
    "annualBalance": [
      {
        "totalCash": 22334308000,
        "totalDebt": 70039716000,
        "totalAssets": 208114647000
      },
      {
        "totalCash": 30200671000,
        "totalDebt": 57288625000,
        "totalAssets": 203536643000
      },
      {
        "totalCash": 40086087000,
        "totalDebt": 44473552000,
        "totalAssets": 234382070000
      },
      {
        "totalCash": 44445034000,
        "totalDebt": 52365908000,
        "totalAssets": 350967145000
      }
    ],
    "annualSBC": [
      374000,
      -18119000,
      -36204000,
      45162000
    ],
    "annualCapex": [
      -36699000,
      -72565000,
      -51279000,
      -129365000
    ]
  }
}