{
  "identifier": {
    "primary": "ISIN",
    "value": "TICKER:OVV"
  },
  "meta": {
    "ticker": "OVV",
    "name": "Ovintiv Inc.",
    "sector": "Energy",
    "industry": "Oil & Gas E&P",
    "region": "NYSE",
    "reportingCurrency": "USD",
    "fetchedAt": "2026-05-09T09:03:58.869Z",
    "filingDate": null,
    "firstTradeDate": "2002-04-08T13:30:00.000Z",
    "ipoYear": 2002
  },
  "marketCap": {
    "value": 16385290240,
    "source": "yahoo_quoteSummary",
    "confidence": 0.9,
    "asOf": "2026-05-09T09:03:58.869Z"
  },
  "metrics": {
    "revenueTTM": {
      "value": 8663000064,
      "source": "yahoo_quoteSummary",
      "confidence": 0.9,
      "asOf": "2026-05-09T09:03:58.869Z"
    },
    "revenueGrowthYoY": {
      "value": -6,
      "source": "yahoo_quoteSummary",
      "confidence": 0.9,
      "asOf": "2026-05-09T09:03:58.869Z"
    },
    "grossMargin": {
      "value": 51.922000000000004,
      "source": "yahoo_quoteSummary",
      "confidence": 0.9,
      "asOf": "2026-05-09T09:03:58.869Z"
    },
    "operatingMargin": {
      "value": 23.807000000000002,
      "source": "yahoo_quoteSummary",
      "confidence": 0.9,
      "asOf": "2026-05-09T09:03:58.869Z"
    },
    "fcfMarginTTM": {
      "value": -16.215513582154813,
      "source": "yahoo_quoteSummary",
      "confidence": 0.9,
      "asOf": "2026-05-09T09:03:58.869Z"
    },
    "sbcRatio": null,
    "insidersOwnership": {
      "value": 0.0044400003,
      "source": "yahoo_quoteSummary",
      "confidence": 0.7,
      "asOf": "2026-05-09T09:03:58.869Z"
    },
    "cashRunway": null,
    "priceSales": {
      "value": 1.8914106,
      "source": "yahoo_quoteSummary",
      "confidence": 0.9,
      "asOf": "2026-05-09T09:03:58.869Z"
    },
    "forwardPE": {
      "value": 7.477798,
      "source": "yahoo_quoteSummary",
      "confidence": 0.9,
      "asOf": "2026-05-09T09:03:58.869Z"
    },
    "pe": {
      "value": 12.098327,
      "source": "yahoo_quoteSummary",
      "confidence": 0.9,
      "asOf": "2026-05-09T09:03:58.869Z"
    }
  },
  "external": {},
  "timeseries": {
    "revenueQ": [
      {
        "value": 2147000000
      },
      {
        "value": 2066000000
      },
      {
        "value": 2318000000
      },
      {
        "value": 2377000000
      },
      {
        "value": 2188000000
      }
    ],
    "opIncQ": [
      {
        "value": 487000000
      },
      {
        "value": 414000000
      },
      {
        "value": 512000000
      },
      {
        "value": 651000000
      },
      {
        "value": 483000000
      }
    ],
    "grossProfitQ": [
      {
        "value": 1233000000
      },
      {
        "value": 1171000000
      },
      {
        "value": 1249000000
      },
      {
        "value": 1343000000
      },
      {
        "value": 1187000000
      }
    ],
    "netIncomeQ": [
      {
        "value": 946000000
      },
      {
        "value": 148000000
      },
      {
        "value": 307000000
      },
      {
        "value": -159000000
      },
      {
        "value": -60000000
      }
    ]
  },
  "annual": {
    "annualRev": [
      {
        "value": 8908000000
      },
      {
        "value": 9152000000
      },
      {
        "value": 10883000000
      },
      {
        "value": 12464000000
      }
    ],
    "annualOpInc": [
      {
        "value": 2064000000
      },
      {
        "value": 2071000000
      },
      {
        "value": 2864000000
      },
      {
        "value": 3853000000
      }
    ],
    "annualNetIncome": [
      {
        "value": 1242000000
      },
      {
        "value": 1125000000
      },
      {
        "value": 2085000000
      },
      {
        "value": 3637000000
      }
    ],
    "annualGP": [
      {
        "value": 4996000000
      },
      {
        "value": 4983000000
      },
      {
        "value": 5901000000
      },
      {
        "value": 6881000000
      }
    ],
    "annualFCF": [
      {
        "value": 1505000000
      },
      {
        "value": 1418000000
      },
      {
        "value": 1423000000
      },
      {
        "value": 2035000000
      }
    ],
    "annualBalance": [
      {
        "totalCash": 35000000,
        "totalDebt": 5202000000,
        "totalAssets": 20390000000
      },
      {
        "totalCash": 42000000,
        "totalDebt": 5453000000,
        "totalAssets": 19254000000
      },
      {
        "totalCash": 3000000,
        "totalDebt": 5737000000,
        "totalAssets": 19987000000
      },
      {
        "totalCash": 5000000,
        "totalDebt": 3570000000,
        "totalAssets": 15056000000
      }
    ],
    "annualSBC": [],
    "annualCapex": [
      -2147000000,
      -2303000000,
      -2744000000,
      -1831000000
    ]
  }
}