{
  "identifier": {
    "primary": "ISIN",
    "value": "TICKER:QAN.AX"
  },
  "meta": {
    "ticker": "QAN.AX",
    "name": "Qantas Airways Limited",
    "sector": "Industrials",
    "industry": "Airlines",
    "region": "ASX",
    "reportingCurrency": "AUD",
    "fetchedAt": "2026-05-09T22:12:06.929Z",
    "filingDate": null,
    "firstTradeDate": "1995-07-31T00:00:00.000Z",
    "ipoYear": 1995
  },
  "marketCap": {
    "value": 8753857382.4,
    "source": "yahoo_quoteSummary",
    "confidence": 0.9,
    "asOf": "2026-05-09T22:12:06.929Z"
  },
  "metrics": {
    "revenueTTM": {
      "value": 24590000128,
      "source": "yahoo_quoteSummary",
      "confidence": 0.9,
      "asOf": "2026-05-09T22:12:06.929Z"
    },
    "revenueGrowthYoY": {
      "value": 6.3,
      "source": "yahoo_quoteSummary",
      "confidence": 0.9,
      "asOf": "2026-05-09T22:12:06.929Z"
    },
    "grossMargin": {
      "value": 33.644,
      "source": "yahoo_quoteSummary",
      "confidence": 0.9,
      "asOf": "2026-05-09T22:12:06.929Z"
    },
    "operatingMargin": {
      "value": 11.399,
      "source": "yahoo_quoteSummary",
      "confidence": 0.9,
      "asOf": "2026-05-09T22:12:06.929Z"
    },
    "fcfMarginTTM": {
      "value": -2.454249812356894,
      "source": "yahoo_quoteSummary",
      "confidence": 0.9,
      "asOf": "2026-05-09T22:12:06.929Z"
    },
    "sbcRatio": null,
    "insidersOwnership": {
      "value": 0.01135,
      "source": "yahoo_quoteSummary",
      "confidence": 0.7,
      "asOf": "2026-05-09T22:12:06.929Z"
    },
    "cashRunway": null,
    "priceSales": {
      "value": 0.54768085,
      "source": "yahoo_quoteSummary",
      "confidence": 0.9,
      "asOf": "2026-05-09T22:12:06.929Z"
    },
    "forwardPE": {
      "value": 8.08356,
      "source": "yahoo_quoteSummary",
      "confidence": 0.9,
      "asOf": "2026-05-09T22:12:06.929Z"
    },
    "pe": {
      "value": 8.396227,
      "source": "yahoo_quoteSummary",
      "confidence": 0.9,
      "asOf": "2026-05-09T22:12:06.929Z"
    }
  },
  "external": {},
  "timeseries": {
    "revenueQ": [],
    "opIncQ": [],
    "grossProfitQ": [],
    "netIncomeQ": []
  },
  "annual": {
    "annualRev": [
      {
        "value": 23823000000
      },
      {
        "value": 21939000000
      },
      {
        "value": 19815000000
      },
      {
        "value": 9108000000
      }
    ],
    "annualOpInc": [
      {
        "value": 2041000000
      },
      {
        "value": 1873000000
      },
      {
        "value": 2440000000
      },
      {
        "value": -1824000000
      }
    ],
    "annualNetIncome": [
      {
        "value": 1605000000
      },
      {
        "value": 1251000000
      },
      {
        "value": 1744000000
      },
      {
        "value": -860000000
      }
    ],
    "annualGP": [
      {
        "value": 12761000000
      },
      {
        "value": 11459000000
      },
      {
        "value": 10970000000
      },
      {
        "value": 4524000000
      }
    ],
    "annualFCF": [
      {
        "value": 448000000
      },
      {
        "value": 768000000
      },
      {
        "value": 2522000000
      },
      {
        "value": 1764000000
      }
    ],
    "annualBalance": [
      {
        "totalCash": 2213000000,
        "totalDebt": 6400000000,
        "totalAssets": 23356000000
      },
      {
        "totalCash": 1718000000,
        "totalDebt": 5035000000,
        "totalAssets": 20564000000
      },
      {
        "totalCash": 3171000000,
        "totalDebt": 5169000000,
        "totalAssets": 20354000000
      },
      {
        "totalCash": 3343000000,
        "totalDebt": 5960000000,
        "totalAssets": 19653000000
      }
    ],
    "annualSBC": [],
    "annualCapex": [
      -3805000000,
      -2673000000,
      -2563000000,
      -906000000
    ]
  }
}