{
  "identifier": {
    "primary": "ISIN",
    "value": "TICKER:SONO"
  },
  "meta": {
    "ticker": "SONO",
    "name": "Sonos, Inc.",
    "sector": "Technology",
    "industry": "Consumer Electronics",
    "region": "NasdaqGS",
    "reportingCurrency": "USD",
    "fetchedAt": "2026-05-13T04:05:41.599Z",
    "filingDate": null,
    "firstTradeDate": "2018-08-02T13:30:00.000Z",
    "ipoYear": 2018
  },
  "marketCap": {
    "value": 1752382720,
    "source": "yahoo_quoteSummary",
    "confidence": 0.9,
    "asOf": "2026-05-13T04:05:41.599Z"
  },
  "metrics": {
    "revenueTTM": {
      "value": 1459852032,
      "source": "yahoo_quoteSummary",
      "confidence": 0.9,
      "asOf": "2026-05-13T04:05:41.599Z"
    },
    "revenueGrowthYoY": {
      "value": 8.4,
      "source": "yahoo_quoteSummary",
      "confidence": 0.9,
      "asOf": "2026-05-13T04:05:41.599Z"
    },
    "grossMargin": {
      "value": 45.007999999999996,
      "source": "yahoo_quoteSummary",
      "confidence": 0.9,
      "asOf": "2026-05-13T04:05:41.599Z"
    },
    "operatingMargin": {
      "value": -9.1120005,
      "source": "yahoo_quoteSummary",
      "confidence": 0.9,
      "asOf": "2026-05-13T04:05:41.599Z"
    },
    "fcfMarginTTM": {
      "value": 8.195145629663376,
      "source": "yahoo_quoteSummary",
      "confidence": 0.9,
      "asOf": "2026-05-13T04:05:41.599Z"
    },
    "sbcRatio": null,
    "insidersOwnership": {
      "value": 0.01944,
      "source": "yahoo_quoteSummary",
      "confidence": 0.7,
      "asOf": "2026-05-13T04:05:41.599Z"
    },
    "cashRunway": null,
    "priceSales": {
      "value": 1.2003838,
      "source": "yahoo_quoteSummary",
      "confidence": 0.9,
      "asOf": "2026-05-13T04:05:41.599Z"
    },
    "forwardPE": {
      "value": 13.62037,
      "source": "yahoo_quoteSummary",
      "confidence": 0.9,
      "asOf": "2026-05-13T04:05:41.599Z"
    },
    "pe": {
      "value": 86.52941,
      "source": "yahoo_quoteSummary",
      "confidence": 0.9,
      "asOf": "2026-05-13T04:05:41.599Z"
    }
  },
  "external": {},
  "timeseries": {
    "revenueQ": [
      {
        "value": 545662000
      },
      {
        "value": 287900000
      },
      {
        "value": 344764000
      },
      {
        "value": 259756000
      },
      {
        "value": 550857000
      }
    ],
    "opIncQ": [
      {
        "value": 100416000
      },
      {
        "value": -27213000
      },
      {
        "value": 390000
      },
      {
        "value": -54225000
      },
      {
        "value": 48093000
      }
    ],
    "grossProfitQ": [
      {
        "value": 253460000
      },
      {
        "value": 125791000
      },
      {
        "value": 149724000
      },
      {
        "value": 113609000
      },
      {
        "value": 241406000
      }
    ],
    "netIncomeQ": [
      {
        "value": 93798000
      },
      {
        "value": -37858000
      },
      {
        "value": -3379000
      },
      {
        "value": -70144000
      },
      {
        "value": 50237000
      }
    ]
  },
  "annual": {
    "annualRev": [
      {
        "value": 1443276000
      },
      {
        "value": 1518056000
      },
      {
        "value": 1655255000
      },
      {
        "value": 1752336000
      }
    ],
    "annualOpInc": [
      {
        "value": -32953000
      },
      {
        "value": -41936000
      },
      {
        "value": -20547000
      },
      {
        "value": 89532000
      }
    ],
    "annualNetIncome": [
      {
        "value": -61144000
      },
      {
        "value": -38146000
      },
      {
        "value": -10274000
      },
      {
        "value": 67383000
      }
    ],
    "annualGP": [
      {
        "value": 630530000
      },
      {
        "value": 689373000
      },
      {
        "value": 716490000
      },
      {
        "value": 796367000
      }
    ],
    "annualFCF": [
      {
        "value": 108193000
      },
      {
        "value": 134659000
      },
      {
        "value": 50120000
      },
      {
        "value": -74476000
      }
    ],
    "annualBalance": [
      {
        "totalCash": 174668000,
        "totalDebt": null,
        "totalAssets": 823278000
      },
      {
        "totalCash": 169732000,
        "totalDebt": null,
        "totalAssets": 916312000
      },
      {
        "totalCash": 220231000,
        "totalDebt": null,
        "totalAssets": 1002241000
      },
      {
        "totalCash": 274855000,
        "totalDebt": null,
        "totalAssets": 1188388000
      }
    ],
    "annualSBC": [
      81564000,
      84294000,
      76857000,
      75640000
    ],
    "annualCapex": [
      -28676000,
      -55247000,
      -50286000,
      -46216000
    ]
  }
}