{
  "identifier": {
    "primary": "ISIN",
    "value": "TICKER:XHR"
  },
  "meta": {
    "ticker": "XHR",
    "name": "Xenia Hotels & Resorts, Inc.",
    "sector": "Real Estate",
    "industry": "REIT - Hotel & Motel",
    "region": "NYSE",
    "reportingCurrency": "USD",
    "fetchedAt": "2026-05-11T16:19:29.095Z",
    "filingDate": null,
    "firstTradeDate": "2015-02-04T14:30:00.000Z",
    "ipoYear": 2015
  },
  "marketCap": {
    "value": 1621673216,
    "source": "yahoo_quoteSummary",
    "confidence": 0.9,
    "asOf": "2026-05-11T16:19:29.095Z"
  },
  "metrics": {
    "revenueTTM": {
      "value": 1084980992,
      "source": "yahoo_quoteSummary",
      "confidence": 0.9,
      "asOf": "2026-05-11T16:19:29.095Z"
    },
    "revenueGrowthYoY": {
      "value": 2.1999999999999997,
      "source": "yahoo_quoteSummary",
      "confidence": 0.9,
      "asOf": "2026-05-11T16:19:29.095Z"
    },
    "grossMargin": {
      "value": 26.327,
      "source": "yahoo_quoteSummary",
      "confidence": 0.9,
      "asOf": "2026-05-11T16:19:29.095Z"
    },
    "operatingMargin": {
      "value": 14.255,
      "source": "yahoo_quoteSummary",
      "confidence": 0.9,
      "asOf": "2026-05-11T16:19:29.095Z"
    },
    "fcfMarginTTM": {
      "value": 11.633176334945414,
      "source": "yahoo_quoteSummary",
      "confidence": 0.9,
      "asOf": "2026-05-11T16:19:29.095Z"
    },
    "sbcRatio": null,
    "insidersOwnership": {
      "value": 0.00861,
      "source": "yahoo_quoteSummary",
      "confidence": 0.7,
      "asOf": "2026-05-11T16:19:29.095Z"
    },
    "cashRunway": null,
    "priceSales": {
      "value": 1.4946558,
      "source": "yahoo_quoteSummary",
      "confidence": 0.9,
      "asOf": "2026-05-11T16:19:29.095Z"
    },
    "forwardPE": {
      "value": 34.206184,
      "source": "yahoo_quoteSummary",
      "confidence": 0.9,
      "asOf": "2026-05-11T16:19:29.095Z"
    },
    "pe": {
      "value": 23.7,
      "source": "yahoo_quoteSummary",
      "confidence": 0.9,
      "asOf": "2026-05-11T16:19:29.095Z"
    }
  },
  "external": {},
  "timeseries": {
    "revenueQ": [
      {
        "value": 295408000
      },
      {
        "value": 265577000
      },
      {
        "value": 236417000
      },
      {
        "value": 287579000
      },
      {
        "value": 288927000
      }
    ],
    "opIncQ": [
      {
        "value": 42110000
      },
      {
        "value": 26735000
      },
      {
        "value": 4206000
      },
      {
        "value": 40497000
      },
      {
        "value": 35864000
      }
    ],
    "grossProfitQ": [
      {
        "value": 87216000
      },
      {
        "value": 68318000
      },
      {
        "value": 45937000
      },
      {
        "value": 84174000
      },
      {
        "value": 78820000
      }
    ],
    "netIncomeQ": [
      {
        "value": 19771000
      },
      {
        "value": 6084000
      },
      {
        "value": -13738000
      },
      {
        "value": 55157000
      },
      {
        "value": 15585000
      }
    ]
  },
  "annual": {
    "annualRev": [
      {
        "value": 1078500000
      },
      {
        "value": 1039047000
      },
      {
        "value": 1025443000
      },
      {
        "value": 997607000
      }
    ],
    "annualOpInc": [
      {
        "value": 107302000
      },
      {
        "value": 85017000
      },
      {
        "value": 97394000
      },
      {
        "value": 110183000
      }
    ],
    "annualNetIncome": [
      {
        "value": 63088000
      },
      {
        "value": 16143000
      },
      {
        "value": 19142000
      },
      {
        "value": 55922000
      }
    ],
    "annualGP": [
      {
        "value": 277249000
      },
      {
        "value": 252314000
      },
      {
        "value": 268166000
      },
      {
        "value": 278151000
      }
    ],
    "annualFCF": [
      {
        "value": 89905000
      },
      {
        "value": 23170000
      },
      {
        "value": 77164000
      },
      {
        "value": 116753000
      }
    ],
    "annualBalance": [
      {
        "totalCash": 140427000,
        "totalDebt": 1422881000,
        "totalAssets": 2808675000
      },
      {
        "totalCash": 78201000,
        "totalDebt": 1334703000,
        "totalAssets": 2831616000
      },
      {
        "totalCash": 164725000,
        "totalDebt": 1394906000,
        "totalAssets": 2902227000
      },
      {
        "totalCash": 305103000,
        "totalDebt": 1429105000,
        "totalAssets": 3080055000
      }
    ],
    "annualSBC": [
      13069000,
      13658000,
      13168000,
      11411000
    ],
    "annualCapex": [
      -86609000,
      -140554000,
      -120905000,
      -70376000
    ]
  }
}